[
    {
        "student_name": "dff",
        "subject": "python",
        "score": 0,
        "total": 5
    },
    {
        "name": "rwet",
        "rollno": "N/A",
        "class": "N/A",
        "department": "N/A",
        "subject": "python",
        "score": 3,
        "total": 25
    },
    {
        "name": "treyt",
        "rollno": "N/A",
        "class": "N/A",
        "department": "N/A",
        "subject": "python",
        "score": 9,
        "total": 25
    },
    {
        "name": "546",
        "rollno": "N/A",
        "class": "N/A",
        "department": "N/A",
        "subject": "python",
        "score": 5,
        "total": 25
    },
    {
        "name": "546",
        "rollno": "N/A",
        "class": "N/A",
        "department": "N/A",
        "subject": "python",
        "score": 5,
        "total": 25
    },
    {
        "name": "546",
        "rollno": "N/A",
        "class": "N/A",
        "department": "N/A",
        "subject": "python",
        "score": 5,
        "total": 25
    },
    {
        "name": "assdf",
        "rollno": "N/A",
        "class": "N/A",
        "department": "N/A",
        "subject": "aptitude",
        "score": 9,
        "total": 25
    },
    {
        "name": "jhfgjh",
        "rollno": "N/A",
        "class": "N/A",
        "department": "N/A",
        "subject": "python",
        "score": 5,
        "total": 25
    },
    {
        "name": "jhfgjh",
        "rollno": "N/A",
        "class": "N/A",
        "department": "N/A",
        "subject": "python",
        "score": 5,
        "total": 25
    },
    {
        "name": "rtt",
        "rollno": "N/A",
        "class": "N/A",
        "department": "N/A",
        "subject": "python",
        "score": 5,
        "total": 25
    },
    {
        "name": "rtt",
        "rollno": "N/A",
        "class": "N/A",
        "department": "N/A",
        "subject": "python",
        "score": 5,
        "total": 25
    },
    {
        "name": "rtt",
        "rollno": "345",
        "class": "ryty",
        "department": "twrt",
        "subject": "python",
        "score": 4,
        "total": 25
    },
    {
        "name": "almubeen",
        "rollno": "23uca039",
        "class": "A",
        "department": "bca",
        "subject": "aptitude",
        "score": 5,
        "total": 25
    }
]